ideastatica_connection_api/__init__.py
ideastatica_connection_api/api_client.py
ideastatica_connection_api/api_response.py
ideastatica_connection_api/configuration.py
ideastatica_connection_api/connection_api_client.py
ideastatica_connection_api/connection_api_service_attacher.py
ideastatica_connection_api/connection_api_service_runner.py
ideastatica_connection_api/exceptions.py
ideastatica_connection_api/py.typed
ideastatica_connection_api/rest.py
ideastatica_connection_api/api/__init__.py
ideastatica_connection_api/api/calculation_api.py
ideastatica_connection_api/api/client_api.py
ideastatica_connection_api/api/connection_api.py
ideastatica_connection_api/api/connection_library_api.py
ideastatica_connection_api/api/conversion_api.py
ideastatica_connection_api/api/export_api.py
ideastatica_connection_api/api/load_effect_api.py
ideastatica_connection_api/api/material_api.py
ideastatica_connection_api/api/member_api.py
ideastatica_connection_api/api/operation_api.py
ideastatica_connection_api/api/parameter_api.py
ideastatica_connection_api/api/presentation_api.py
ideastatica_connection_api/api/project_api.py
ideastatica_connection_api/api/report_api.py
ideastatica_connection_api/api/settings_api.py
ideastatica_connection_api/api/template_api.py
ideastatica_connection_api/api_ext/__init__.py
ideastatica_connection_api/api_ext/export_ext_api.py
ideastatica_connection_api/api_ext/project_ext_api.py
ideastatica_connection_api/api_ext/report_ext_api.py
ideastatica_connection_api/models/__init__.py
ideastatica_connection_api/models/anchor_grid.py
ideastatica_connection_api/models/anchor_type.py
ideastatica_connection_api/models/base_template_conversion.py
ideastatica_connection_api/models/beam_data.py
ideastatica_connection_api/models/bend_data.py
ideastatica_connection_api/models/bolt_grid.py
ideastatica_connection_api/models/bolt_shear_type.py
ideastatica_connection_api/models/buckling_res.py
ideastatica_connection_api/models/check_res_anchor.py
ideastatica_connection_api-25.1.3.1326.dist-info/METADATA
ideastatica_connection_api-25.1.3.1326.dist-info/WHEEL
ideastatica_connection_api-25.1.3.1326.dist-info/top_level.txt
ideastatica_connection_api-25.1.3.1326.dist-info/RECORD
