Metadata-Version: 2.4
Name: ideastatica-connection-api
Version: 25.1.3.1326
Summary: Connection Rest API 3.0
Home-page: 
Author: IDEA StatiCa
Author-email: info@ideastatica.com
License: IDEA StatiCa License
Keywords: OpenAPI,OpenAPI-Generator,Connection Rest API 3.0
Requires-Dist: urllib3<3.0.0,>=1.25.3
Requires-Dist: python-dateutil>=2.8.2
Requires-Dist: pydantic>=2
Requires-Dist: typing-extensions>=4.7.1
Dynamic: author
Dynamic: author-email
Dynamic: description
Dynamic: description-content-type
Dynamic: keywords
Dynamic: license
Dynamic: requires-dist
Dynamic: summary
